mismo/__init__.py
mismo/_common.py
mismo/_counts_table.py
mismo/_data/_datasets/febrl/dataset1.csv
mismo/_data/_datasets/febrl/dataset2.csv
mismo/_data/_datasets/febrl/dataset3.csv
mismo/_data/_datasets/leipzig/affiliations.csv
mismo/_data/_datasets/leipzig/make_affiliations.py
mismo/_data/_datasets/patstat/patents.csv
mismo/_data/_datasets/rldata/RLdata10000.csv
mismo/_data/_datasets/rldata/RLdata500.csv
mismo/_datasets.py
mismo/_explain.py
mismo/_factorizer.py
mismo/_funcs.py
mismo/_n_naive.py
mismo/_recipe.py
mismo/_registry.py
mismo/_resolve.py
mismo/_structs.py
mismo/_typing.py
mismo/_upset.py
mismo/_util.py
mismo/arrays/__init__.py
mismo/arrays/_array.py
mismo/arrays/_builtins.py
mismo/arrays/tests/test_array.py
mismo/cluster/__init__.py
mismo/cluster/_connected_components.py
mismo/cluster/_dashboard.py
mismo/cluster/_dashboard_internal.py
mismo/cluster/_eval.py
mismo/cluster/_metrics.py
mismo/cluster/_subgraph.py
mismo/cluster/_subgraph_internal.py
mismo/cluster/test/test_connected_components.py
mismo/cluster/test/test_eval.py
mismo/compare/__init__.py
mismo/compare/_comparer.py
mismo/compare/_match_level.py
mismo/compare/_plot.py
mismo/compare/tests/test_match_level.py
mismo/conftest.py
mismo/eda/__init__.py
mismo/eda/_plot.py
mismo/exceptions.py
mismo/fs/__init__.py
mismo/fs/_plot.py
mismo/fs/_train.py
mismo/fs/_train_em.py
mismo/fs/_util.py
mismo/fs/_weights.py
mismo/fs/tests/test_train.py
mismo/fs/tests/test_weights.py
mismo/joins/__init__.py
mismo/joins/_analyze.py
mismo/joins/_conditions.py
mismo/joins/_core.py
mismo/joins/tests/test_conditions.py
mismo/joins/tests/test_join.py
mismo/lib/__init__.py
mismo/lib/email/__init__.py
mismo/lib/email/_core.py
mismo/lib/email/tests/test_core.py
mismo/lib/geo/__init__.py
mismo/lib/geo/_address.py
mismo/lib/geo/_census.py
mismo/lib/geo/_latlon.py
mismo/lib/geo/_postal.py
mismo/lib/geo/_regex_parse.py
mismo/lib/geo/_spacy.py
mismo/lib/geo/tests/.gitignore
mismo/lib/geo/tests/test_address.py
mismo-0.3.0.dist-info/WHEEL
mismo-0.3.0.dist-info/METADATA
mismo-0.3.0.dist-info/RECORD
