Metadata-Version: 2.3
Name: mismo
Version: 0.3.0
Summary: The SQL/Ibis powered sklearn of record linkage.
Keywords: record linkage,entity resolution,fuzzy linking,machine learning,ibis,sql,splink,duckdb
Author: Nick Crews
Author-email: Nick Crews <nicholas.b.crews@gmail.com>
License: LGPL-3.0-or-later
Classifier: Development Status :: 3 - Alpha
Classifier: Programming Language :: Python
Classifier: Programming Language :: Python :: 3.10
Classifier: Programming Language :: Python :: 3.11
Classifier: Programming Language :: Python :: 3.12
Classifier: Programming Language :: Python :: 3.13
Classifier: Programming Language :: Python :: Implementation :: CPython
Classifier: Programming Language :: Python :: Implementation :: PyPy
Requires-Dist: ibis-framework>=9.1.0
Requires-Dist: sqlglot>=25.29.0
Requires-Dist: typing-extensions>=4.0.0 ; python_full_version < '3.11'
Requires-Dist: scikit-learn>=1.5.2 ; extra == 'metrics'
Requires-Dist: postal>=1.1.7,<1.1.11 ; (sys_platform == 'darwin' and extra == 'postal') or (sys_platform == 'linux' and extra == 'postal')
Requires-Dist: en-us-address-ner-sm ; extra == 'spacy'
Requires-Dist: spacy>=3.8.2 ; extra == 'spacy'
Requires-Dist: altair>=5.0.0 ; extra == 'viz'
Requires-Dist: ipywidgets>=7.5.1 ; extra == 'viz'
Requires-Dist: solara-ui>=1.51.0 ; extra == 'viz'
Requires-Dist: anywidget>=0.9.18 ; extra == 'viz'
Requires-Python: >=3.10
Project-URL: Documentation, https://nickcrews.github.io/mismo
Project-URL: Homepage, https://github.com/NickCrews/mismo
Project-URL: Issues, https://github.com/NickCrews/mismo/issues
Project-URL: Source, https://github.com/NickCrews/mismo
Provides-Extra: metrics
Provides-Extra: postal
Provides-Extra: spacy
Provides-Extra: viz
